README.md
setup.py
fast_server/__init__.py
fast_server/fast.py
fast_server.egg-info/PKG-INFO
fast_server.egg-info/SOURCES.txt
fast_server.egg-info/dependency_links.txt
fast_server.egg-info/top_level.txt
fast_server/application/__init__.py
fast_server/application/annotation.py
fast_server/application/cookies.py
fast_server/application/fast_http.py
fast_server/application/futures.py
fast_server/application/thread_pool.py
fast_server/application/tools.py
fast_server/application/wsgi_app.py
fast_server/container/__init__.py
fast_server/container/container.py
fast_server/container/fast_ip.py
fast_server/container/log.py
fast_server/container/setting.py